Metadata-Version: 2.1
Name: matplotlib-pdf
Version: 0.1.7
Summary: Maintain a PDF-file with Matplotlib figures as pages.
Home-page: https://github.com/NorthGuard/matplotlib_pdf
Author: Jeppe Nørregaard
Author-email: northguard_serve@tutanota.com
License: MIT License
Keywords: matplotlib pdf figure
Classifier: Programming Language :: Python :: 3
Requires-Python: >=3.0
License-File: LICENSE
